saad_data_pipeline/analysis.py
saad_data_pipeline/cleaning.py
saad_data_pipeline/config.py
saad_data_pipeline/ingestion.py
saad_data_pipeline/main.py
saad_data_pipeline/profile_report.py
saad_data_pipeline/transformation.py
saad_data_pipeline/utils.py
saad_data_pipeline-0.1.0.dist-info/METADATA
saad_data_pipeline-0.1.0.dist-info/WHEEL
saad_data_pipeline-0.1.0.dist-info/entry_points.txt
saad_data_pipeline-0.1.0.dist-info/top_level.txt
saad_data_pipeline-0.1.0.dist-info/RECORD
