Metadata-Version: 2.4
Name: saad-data-pipeline
Version: 0.1.0
Summary: A data pipeline and analytics toolkit
Author-email: Saad Khalmadani <saad.khalmadani@gmail.com>
License: MIT
Requires-Python: >=3.12
Requires-Dist: dotenv>=0.9.9
Requires-Dist: hypothesis>=6.136.8
Requires-Dist: pandas>=2.3.1
Requires-Dist: pandera>=0.25.0
Requires-Dist: pycountry>=24.6.1
Requires-Dist: ydata-profiling>=4.16.1
